azure/mgmt/edgegateway/__init__.py
azure/mgmt/edgegateway/data_box_edge_management_client.py
azure/mgmt/edgegateway/version.py
azure/mgmt/edgegateway/models/__init__.py
azure/mgmt/edgegateway/models/address.py
azure/mgmt/edgegateway/models/address_py3.py
azure/mgmt/edgegateway/models/alert.py
azure/mgmt/edgegateway/models/alert_error_details.py
azure/mgmt/edgegateway/models/alert_error_details_py3.py
azure/mgmt/edgegateway/models/alert_paged.py
azure/mgmt/edgegateway/models/alert_py3.py
azure/mgmt/edgegateway/models/arm_base_model.py
azure/mgmt/edgegateway/models/arm_base_model_py3.py
azure/mgmt/edgegateway/models/asymmetric_encrypted_secret.py
azure/mgmt/edgegateway/models/asymmetric_encrypted_secret_py3.py
azure/mgmt/edgegateway/models/authentication.py
azure/mgmt/edgegateway/models/authentication_py3.py
azure/mgmt/edgegateway/models/azure_container_info.py
azure/mgmt/edgegateway/models/azure_container_info_py3.py
azure/mgmt/edgegateway/models/bandwidth_schedule.py
azure/mgmt/edgegateway/models/bandwidth_schedule_paged.py
azure/mgmt/edgegateway/models/bandwidth_schedule_py3.py
azure/mgmt/edgegateway/models/client_access_right.py
azure/mgmt/edgegateway/models/client_access_right_py3.py
azure/mgmt/edgegateway/models/contact_details.py
azure/mgmt/edgegateway/models/contact_details_py3.py
azure/mgmt/edgegateway/models/data_box_edge_device.py
azure/mgmt/edgegateway/models/data_box_edge_device_extended_info.py
azure/mgmt/edgegateway/models/data_box_edge_device_extended_info_py3.py
azure/mgmt/edgegateway/models/data_box_edge_device_paged.py
azure/mgmt/edgegateway/models/data_box_edge_device_patch.py
azure/mgmt/edgegateway/models/data_box_edge_device_patch_py3.py
azure/mgmt/edgegateway/models/data_box_edge_device_py3.py
azure/mgmt/edgegateway/models/data_box_edge_management_client_enums.py
azure/mgmt/edgegateway/models/file_event_trigger.py
azure/mgmt/edgegateway/models/file_event_trigger_py3.py
azure/mgmt/edgegateway/models/file_source_info.py
azure_mgmt_edgegateway-0.1.0.dist-info/METADATA
azure_mgmt_edgegateway-0.1.0.dist-info/WHEEL
azure_mgmt_edgegateway-0.1.0.dist-info/top_level.txt
azure_mgmt_edgegateway-0.1.0.dist-info/RECORD
